app2/__init__.py
app2/main.py
app2/api/__init__.py
app2/api/endpoints.py
app2/api/http_status_codes.py
app2/authentication/__init__.py
app2/authentication/authentication.py
app2/helpers/__init__.py
app2/helpers/root_dir.py
app2/logging/__init__.py
app2/logging/logging_config.py
app2/ui/__init__.py
app2/ui/index.py
app2/ui/jinja.py
app2/ui/templates/__init__.py
app2/ui/templates/index.html
app2-0.0.0.dist-info/METADATA
app2-0.0.0.dist-info/WHEEL
app2-0.0.0.dist-info/top_level.txt
app2-0.0.0.dist-info/RECORD
