Metadata-Version: 2.1
Name: app2
Version: 0.0.0
Summary: Kortical cloud app
Home-page: UNKNOWN
Author: UNKNOWN
Author-email: UNKNOWN
License: UNKNOWN
Platform: UNKNOWN
